gingerjs/__init__.py
gingerjs/SSR/__init__.py
gingerjs/SSR/routes.js
gingerjs/SSR/ssr.py
gingerjs/app/__init__.py
gingerjs/app/app.py
gingerjs/create_app/__init__.py
gingerjs/create_app/create_app.py
gingerjs/create_app/load_settings.py
gingerjs/create_app/logger.py
gingerjs/create_app/main.py
gingerjs/create_app/svgr-loader.js
gingerjs/create_app/webpack.config.js
gingerjs/create_app/app/components.json
gingerjs/create_app/app/jsconfig.json
gingerjs/create_app/app/main.py
gingerjs/create_app/app/package.json
gingerjs/create_app/app/postcss.config.js
gingerjs/create_app/app/settings.py
gingerjs/create_app/app/tailwind.config.js
gingerjs/create_app/app/public/templates/bad_request_exception_template.html
gingerjs/create_app/app/public/templates/exception_template.html
gingerjs/create_app/app/public/templates/exception_template_debug.html
gingerjs/create_app/app/public/templates/index.html
gingerjs/create_app/app/public/templates/internal_server_exception_template.html
gingerjs/create_app/app/public/templates/layout.html
gingerjs/create_app/app/public/templates/not_found.html
gingerjs/create_app/app/src/global.css
gingerjs/create_app/app/src/app/index.jsx
gingerjs/create_app/app/src/app/index.py
gingerjs/create_app/app/src/app/layout.jsx
gingerjs/create_app/app/src/app/api/test/index.py
gingerjs/create_app/app/src/libs/Link.jsx
gingerjs/create_app/app/src/libs/navigate.jsx
gingerjs/create_app/app/src/libs/theme-provider.jsx
gingerjs/create_app/app/src/libs/utils.js
gingerjs/create_app/routes/__init__.py
gingerjs/create_app/routes/flask/__init__.py
gingerjs/create_app/routes/flask/api.py
gingerjs/create_app/routes/flask/exception_view.py
gingerjs/create_app/routes/flask/layout_view.py
gingerjs/create_app/routes/flask/middleware.py
gingerjs/create_app/routes/flask/not_found.py
gingerjs/create_app/routes/flask/view.py
gingerjs/js_bridge/__init__.py
gingerjs/js_bridge/unix_sock.js
ginger_js-0.0.3.dist-info/LICENSE
ginger_js-0.0.3.dist-info/METADATA
ginger_js-0.0.3.dist-info/WHEEL
ginger_js-0.0.3.dist-info/entry_points.txt
ginger_js-0.0.3.dist-info/top_level.txt
ginger_js-0.0.3.dist-info/RECORD
