Metadata-Version: 2.1
Name: ginger_js
Version: 0.0.3
Summary: A Truly Full-Stack Development Experience with Python and React
Home-page: https://github.com/ginger-society/ginger-js
Author: py-react
Author-email: yksandeep08+reactpy@gmail.com
Classifier: License :: OSI Approved :: MIT License
Classifier: Operating System :: OS Independent
Requires-Python: >=3.11.0
License-File: LICENSE
Requires-Dist: fastapi ==0.111.1
Requires-Dist: watchdog ==4.0.1
Requires-Dist: psutil ==6.0.0
